structure_embedding/__init__.py
structure_embedding/data.py
structure_embedding/plot.py
structure_embedding/transformer.py
structure_embedding/utils.py
structure_embedding/transformers/__init__.py
structure_embedding/transformers/umap.py
structure_embedding-0.0.8.dist-info/LICENSE
structure_embedding-0.0.8.dist-info/METADATA
structure_embedding-0.0.8.dist-info/WHEEL
structure_embedding-0.0.8.dist-info/top_level.txt
structure_embedding-0.0.8.dist-info/RECORD
