Metadata-Version: 2.2
Name: structure-embedding
Version: 0.0.8
Summary: Simplifying workflows for generating embeddings of structures.
Author-email: Thomas Nicholas <tcnicholas@me.com>
License: MIT License
Classifier: License :: OSI Approved :: MIT License
Classifier: Programming Language :: Python
Classifier: Programming Language :: Python :: 3
Requires-Python: >=3.9
License-File: LICENSE
Requires-Dist: matplotlib>=3.9.4
Requires-Dist: scipy>=1.13.1
Requires-Dist: umap-learn>=0.5.7
Provides-Extra: publish
Requires-Dist: build; extra == "publish"
Requires-Dist: twine; extra == "publish"
